{"tasks": {"1": {"title": "Prueba Tarea 1", "description": "Esta es la prueba inicial de agregar una tarea.", "due_date": "2024-09-05", "tag": "Prueba", "status": "Atrasada"}, "2": {"title": "Prueba tarea 2", "description": "otra prueba mas", "due_date": "2024-09-05", "tag": "urgente", "status": "Atrasada"}, "3": {"title": "certamen pruebas de software", "description": "uff certamen ", "due_date": "2025-01-01", "tag": "urgente", "status": "Pendiente"}}, "users": {"1": {"nombre": "usuario1", "password": "f6a47a638824180d57f0a561fd5843c6"}, "2": {"nombre": "usuario2", "password": "f6a47a638824180d57f0a561fd5843c6"}, "3": {"nombre": "usuario3", "password": "f6a47a638824180d57f0a561fd5843c6"}}}